[
  {
    "gameId": 2025020931,
    "teamAbbrev": "WSH",
    "homeRoadFlag": "H",
    "gameDate": "2026-02-27",
    "goals": 0,
    "assists": 0,
    "commonName": {
      "default": "Capitals"
    },
    "opponentCommonName": {
      "default": "Golden Knights"
    },
    "gamesStarted": 1,
    "decision": "W",
    "shotsAgainst": 26,
    "goalsAgainst": 2,
    "savePctg": 0.923077,
    "shutouts": 0,
    "opponentAbbrev": "VGK",
    "pim": 0,
    "toi": "59:49"
  },
  {
    "gameId": 2025020911,
    "teamAbbrev": "WSH",
    "homeRoadFlag": "H",
    "gameDate": "2026-02-25",
    "goals": 0,
    "assists": 0,
    "commonName": {
      "default": "Capitals"
    },
    "opponentCommonName": {
      "default": "Flyers"
    },
    "gamesStarted": 1,
    "decision": "W",
    "shotsAgainst": 24,
    "goalsAgainst": 1,
    "savePctg": 0.958333,
    "shutouts": 0,
    "opponentAbbrev": "PHI",
    "pim": 0,
    "toi": "60:00"
  },
  {
    "gameId": 2025020908,
    "teamAbbrev": "WSH",
    "homeRoadFlag": "H",
    "gameDate": "2026-02-05",
    "goals": 0,
    "assists": 0,
    "commonName": {
      "default": "Capitals"
    },
    "opponentCommonName": {
      "default": "Predators"
    },
    "gamesStarted": 1,
    "decision": "W",
    "shotsAgainst": 29,
    "goalsAgainst": 2,
    "savePctg": 0.931034,
    "shutouts": 0,
    "opponentAbbrev": "NSH",
    "pim": 0,
    "toi": "59:16"
  },
  {
    "gameId": 2025020839,
    "teamAbbrev": "WSH",
    "homeRoadFlag": "R",
    "gameDate": "2026-01-27",
    "goals": 0,
    "assists": 0,
    "commonName": {
      "default": "Capitals"
    },
    "opponentCommonName": {
      "default": "Kraken"
    },
    "gamesStarted": 1,
    "decision": "L",
    "shotsAgainst": 32,
    "goalsAgainst": 5,
    "savePctg": 0.84375,
    "shutouts": 0,
    "opponentAbbrev": "SEA",
    "pim": 0,
    "toi": "60:00"
  },
  {
    "gameId": 2025020806,
    "teamAbbrev": "WSH",
    "homeRoadFlag": "R",
    "gameDate": "2026-01-23",
    "goals": 0,
    "assists": 0,
    "commonName": {
      "default": "Capitals"
    },
    "opponentCommonName": {
      "default": "Flames"
    },
    "gamesStarted": 1,
    "decision": "W",
    "shotsAgainst": 26,
    "goalsAgainst": 1,
    "savePctg": 0.961538,
    "shutouts": 0,
    "opponentAbbrev": "CGY",
    "pim": 0,
    "toi": "59:52"
  },
  {
    "gameId": 2025020792,
    "teamAbbrev": "WSH",
    "homeRoadFlag": "R",
    "gameDate": "2026-01-21",
    "goals": 0,
    "assists": 0,
    "commonName": {
      "default": "Capitals"
    },
    "opponentCommonName": {
      "default": "Canucks"
    },
    "gamesStarted": 1,
    "decision": "L",
    "shotsAgainst": 25,
    "goalsAgainst": 4,
    "savePctg": 0.84,
    "shutouts": 0,
    "opponentAbbrev": "VAN",
    "pim": 0,
    "toi": "56:57"
  },
  {
    "gameId": 2025020761,
    "teamAbbrev": "WSH",
    "homeRoadFlag": "H",
    "gameDate": "2026-01-17",
    "goals": 0,
    "assists": 0,
    "commonName": {
      "default": "Capitals"
    },
    "opponentCommonName": {
      "default": "Panthers"
    },
    "gamesStarted": 1,
    "decision": "L",
    "shotsAgainst": 29,
    "goalsAgainst": 3,
    "savePctg": 0.896552,
    "shutouts": 0,
    "opponentAbbrev": "FLA",
    "pim": 0,
    "toi": "59:37"
  },
  {
    "gameId": 2025020742,
    "teamAbbrev": "WSH",
    "homeRoadFlag": "H",
    "gameDate": "2026-01-15",
    "goals": 0,
    "assists": 0,
    "commonName": {
      "default": "Capitals"
    },
    "opponentCommonName": {
      "default": "Sharks"
    },
    "gamesStarted": 1,
    "decision": "L",
    "shotsAgainst": 26,
    "goalsAgainst": 3,
    "savePctg": 0.884615,
    "shutouts": 0,
    "opponentAbbrev": "SJS",
    "pim": 0,
    "toi": "57:01"
  },
  {
    "gameId": 2025020727,
    "teamAbbrev": "WSH",
    "homeRoadFlag": "H",
    "gameDate": "2026-01-13",
    "goals": 0,
    "assists": 0,
    "commonName": {
      "default": "Capitals"
    },
    "opponentCommonName": {
      "default": "Canadiens"
    },
    "gamesStarted": 1,
    "decision": "W",
    "shotsAgainst": 25,
    "goalsAgainst": 2,
    "savePctg": 0.92,
    "shutouts": 0,
    "opponentAbbrev": "MTL",
    "pim": 0,
    "toi": "63:52"
  },
  {
    "gameId": 2025020694,
    "teamAbbrev": "WSH",
    "homeRoadFlag": "R",
    "gameDate": "2026-01-09",
    "goals": 0,
    "assists": 0,
    "commonName": {
      "default": "Capitals"
    },
    "opponentCommonName": {
      "default": "Blackhawks"
    },
    "gamesStarted": 1,
    "decision": "W",
    "shotsAgainst": 24,
    "goalsAgainst": 1,
    "savePctg": 0.958333,
    "shutouts": 0,
    "opponentAbbrev": "CHI",
    "pim": 0,
    "toi": "60:00"
  },
  {
    "gameId": 2025020677,
    "teamAbbrev": "WSH",
    "homeRoadFlag": "H",
    "gameDate": "2026-01-07",
    "goals": 0,
    "assists": 0,
    "commonName": {
      "default": "Capitals"
    },
    "opponentCommonName": {
      "default": "Stars"
    },
    "gamesStarted": 1,
    "decision": "L",
    "shotsAgainst": 35,
    "goalsAgainst": 3,
    "savePctg": 0.914286,
    "shutouts": 0,
    "opponentAbbrev": "DAL",
    "pim": 0,
    "toi": "58:02"
  },
  {
    "gameId": 2025020652,
    "teamAbbrev": "WSH",
    "homeRoadFlag": "H",
    "gameDate": "2026-01-03",
    "goals": 0,
    "assists": 0,
    "commonName": {
      "default": "Capitals"
    },
    "opponentCommonName": {
      "default": "Blackhawks"
    },
    "gamesStarted": 1,
    "decision": "O",
    "shotsAgainst": 33,
    "goalsAgainst": 2,
    "savePctg": 0.939394,
    "shutouts": 0,
    "opponentAbbrev": "CHI",
    "pim": 0,
    "toi": "65:00"
  },
  {
    "gameId": 2025020632,
    "teamAbbrev": "WSH",
    "homeRoadFlag": "R",
    "gameDate": "2026-01-01",
    "goals": 0,
    "assists": 0,
    "commonName": {
      "default": "Capitals"
    },
    "opponentCommonName": {
      "default": "Senators",
      "fr": "Sénateurs"
    },
    "gamesStarted": 1,
    "decision": "L",
    "shotsAgainst": 32,
    "goalsAgainst": 4,
    "savePctg": 0.875,
    "shutouts": 0,
    "opponentAbbrev": "OTT",
    "pim": 0,
    "toi": "57:45"
  },
  {
    "gameId": 2025020607,
    "teamAbbrev": "WSH",
    "homeRoadFlag": "R",
    "gameDate": "2025-12-29",
    "goals": 0,
    "assists": 0,
    "commonName": {
      "default": "Capitals"
    },
    "opponentCommonName": {
      "default": "Panthers"
    },
    "gamesStarted": 1,
    "decision": "L",
    "shotsAgainst": 28,
    "goalsAgainst": 4,
    "savePctg": 0.857143,
    "shutouts": 0,
    "opponentAbbrev": "FLA",
    "pim": 0,
    "toi": "58:45"
  },
  {
    "gameId": 2025020592,
    "teamAbbrev": "WSH",
    "homeRoadFlag": "R",
    "gameDate": "2025-12-27",
    "goals": 0,
    "assists": 0,
    "commonName": {
      "default": "Capitals"
    },
    "opponentCommonName": {
      "default": "Devils"
    },
    "gamesStarted": 1,
    "decision": "W",
    "shotsAgainst": 38,
    "goalsAgainst": 3,
    "savePctg": 0.921053,
    "shutouts": 0,
    "opponentAbbrev": "NJD",
    "pim": 0,
    "toi": "64:06"
  },
  {
    "gameId": 2025020576,
    "teamAbbrev": "WSH",
    "homeRoadFlag": "H",
    "gameDate": "2025-12-23",
    "goals": 0,
    "assists": 0,
    "commonName": {
      "default": "Capitals"
    },
    "opponentCommonName": {
      "default": "Rangers"
    },
    "gamesStarted": 1,
    "decision": "L",
    "shotsAgainst": 20,
    "goalsAgainst": 6,
    "savePctg": 0.7,
    "shutouts": 0,
    "opponentAbbrev": "NYR",
    "pim": 0,
    "toi": "58:17"
  },
  {
    "gameId": 2025020550,
    "teamAbbrev": "WSH",
    "homeRoadFlag": "H",
    "gameDate": "2025-12-20",
    "goals": 0,
    "assists": 0,
    "commonName": {
      "default": "Capitals"
    },
    "opponentCommonName": {
      "default": "Red Wings"
    },
    "gamesStarted": 1,
    "decision": "L",
    "shotsAgainst": 40,
    "goalsAgainst": 4,
    "savePctg": 0.9,
    "shutouts": 0,
    "opponentAbbrev": "DET",
    "pim": 0,
    "toi": "58:48"
  },
  {
    "gameId": 2025020539,
    "teamAbbrev": "WSH",
    "homeRoadFlag": "H",
    "gameDate": "2025-12-18",
    "goals": 0,
    "assists": 0,
    "commonName": {
      "default": "Capitals"
    },
    "opponentCommonName": {
      "default": "Maple Leafs"
    },
    "gamesStarted": 1,
    "decision": "W",
    "shotsAgainst": 22,
    "goalsAgainst": 0,
    "savePctg": 1.0,
    "shutouts": 1,
    "opponentAbbrev": "TOR",
    "pim": 0,
    "toi": "59:48"
  },
  {
    "gameId": 2025020503,
    "teamAbbrev": "WSH",
    "homeRoadFlag": "R",
    "gameDate": "2025-12-13",
    "goals": 0,
    "assists": 0,
    "commonName": {
      "default": "Capitals"
    },
    "opponentCommonName": {
      "default": "Jets"
    },
    "gamesStarted": 1,
    "decision": "L",
    "shotsAgainst": 35,
    "goalsAgainst": 5,
    "savePctg": 0.857143,
    "shutouts": 0,
    "opponentAbbrev": "WPG",
    "pim": 0,
    "toi": "59:53"
  },
  {
    "gameId": 2025020485,
    "teamAbbrev": "WSH",
    "homeRoadFlag": "H",
    "gameDate": "2025-12-11",
    "goals": 0,
    "assists": 0,
    "commonName": {
      "default": "Capitals"
    },
    "opponentCommonName": {
      "default": "Hurricanes"
    },
    "gamesStarted": 1,
    "decision": "O",
    "shotsAgainst": 39,
    "goalsAgainst": 2,
    "savePctg": 0.948718,
    "shutouts": 0,
    "opponentAbbrev": "CAR",
    "pim": 0,
    "toi": "65:00"
  },
  {
    "gameId": 2025020459,
    "teamAbbrev": "WSH",
    "homeRoadFlag": "H",
    "gameDate": "2025-12-07",
    "goals": 0,
    "assists": 0,
    "commonName": {
      "default": "Capitals"
    },
    "opponentCommonName": {
      "default": "Blue Jackets"
    },
    "gamesStarted": 1,
    "decision": "W",
    "shotsAgainst": 39,
    "goalsAgainst": 0,
    "savePctg": 1.0,
    "shutouts": 1,
    "opponentAbbrev": "CBJ",
    "pim": 0,
    "toi": "59:49"
  },
  {
    "gameId": 2025020440,
    "teamAbbrev": "WSH",
    "homeRoadFlag": "R",
    "gameDate": "2025-12-05",
    "goals": 0,
    "assists": 0,
    "commonName": {
      "default": "Capitals"
    },
    "opponentCommonName": {
      "default": "Ducks"
    },
    "gamesStarted": 1,
    "decision": "O",
    "shotsAgainst": 38,
    "goalsAgainst": 3,
    "savePctg": 0.921053,
    "shutouts": 0,
    "opponentAbbrev": "ANA",
    "pim": 0,
    "toi": "65:00"
  },
  {
    "gameId": 2025020420,
    "teamAbbrev": "WSH",
    "homeRoadFlag": "R",
    "gameDate": "2025-12-02",
    "goals": 0,
    "assists": 0,
    "commonName": {
      "default": "Capitals"
    },
    "opponentCommonName": {
      "default": "Kings"
    },
    "gamesStarted": 1,
    "decision": "W",
    "shotsAgainst": 25,
    "goalsAgainst": 1,
    "savePctg": 0.96,
    "shutouts": 0,
    "opponentAbbrev": "LAK",
    "pim": 0,
    "toi": "60:00"
  },
  {
    "gameId": 2025020402,
    "teamAbbrev": "WSH",
    "homeRoadFlag": "R",
    "gameDate": "2025-11-30",
    "goals": 0,
    "assists": 0,
    "commonName": {
      "default": "Capitals"
    },
    "opponentCommonName": {
      "default": "Islanders"
    },
    "gamesStarted": 1,
    "decision": "W",
    "shotsAgainst": 31,
    "goalsAgainst": 1,
    "savePctg": 0.967742,
    "shutouts": 0,
    "opponentAbbrev": "NYI",
    "pim": 0,
    "toi": "60:00"
  },
  {
    "gameId": 2025020386,
    "teamAbbrev": "WSH",
    "homeRoadFlag": "H",
    "gameDate": "2025-11-28",
    "goals": 0,
    "assists": 0,
    "commonName": {
      "default": "Capitals"
    },
    "opponentCommonName": {
      "default": "Maple Leafs"
    },
    "gamesStarted": 1,
    "decision": "W",
    "shotsAgainst": 22,
    "goalsAgainst": 2,
    "savePctg": 0.909091,
    "shutouts": 0,
    "opponentAbbrev": "TOR",
    "pim": 0,
    "toi": "60:00"
  },
  {
    "gameId": 2025020356,
    "teamAbbrev": "WSH",
    "homeRoadFlag": "H",
    "gameDate": "2025-11-24",
    "goals": 0,
    "assists": 0,
    "commonName": {
      "default": "Capitals"
    },
    "opponentCommonName": {
      "default": "Blue Jackets"
    },
    "gamesStarted": 1,
    "decision": "W",
    "shotsAgainst": 23,
    "goalsAgainst": 1,
    "savePctg": 0.956522,
    "shutouts": 0,
    "opponentAbbrev": "CBJ",
    "pim": 0,
    "toi": "60:00"
  },
  {
    "gameId": 2025020341,
    "teamAbbrev": "WSH",
    "homeRoadFlag": "H",
    "gameDate": "2025-11-22",
    "goals": 0,
    "assists": 0,
    "commonName": {
      "default": "Capitals"
    },
    "opponentCommonName": {
      "default": "Lightning"
    },
    "gamesStarted": 1,
    "decision": "L",
    "shotsAgainst": 6,
    "goalsAgainst": 4,
    "savePctg": 0.333333,
    "shutouts": 0,
    "opponentAbbrev": "TBL",
    "pim": 0,
    "toi": "18:19"
  },
  {
    "gameId": 2025020315,
    "teamAbbrev": "WSH",
    "homeRoadFlag": "H",
    "gameDate": "2025-11-19",
    "goals": 0,
    "assists": 0,
    "commonName": {
      "default": "Capitals"
    },
    "opponentCommonName": {
      "default": "Oilers"
    },
    "gamesStarted": 1,
    "decision": "W",
    "shotsAgainst": 30,
    "goalsAgainst": 4,
    "savePctg": 0.866667,
    "shutouts": 0,
    "opponentAbbrev": "EDM",
    "pim": 0,
    "toi": "60:00"
  },
  {
    "gameId": 2025020288,
    "teamAbbrev": "WSH",
    "homeRoadFlag": "H",
    "gameDate": "2025-11-15",
    "goals": 0,
    "assists": 0,
    "commonName": {
      "default": "Capitals"
    },
    "opponentCommonName": {
      "default": "Devils"
    },
    "gamesStarted": 1,
    "decision": "O",
    "shotsAgainst": 31,
    "goalsAgainst": 2,
    "savePctg": 0.935484,
    "shutouts": 0,
    "opponentAbbrev": "NJD",
    "pim": 0,
    "toi": "65:00"
  },
  {
    "gameId": 2025020273,
    "teamAbbrev": "WSH",
    "homeRoadFlag": "R",
    "gameDate": "2025-11-13",
    "goals": 0,
    "assists": 0,
    "commonName": {
      "default": "Capitals"
    },
    "opponentCommonName": {
      "default": "Panthers"
    },
    "gamesStarted": 1,
    "decision": "L",
    "shotsAgainst": 27,
    "goalsAgainst": 5,
    "savePctg": 0.814815,
    "shutouts": 0,
    "opponentAbbrev": "FLA",
    "pim": 0,
    "toi": "59:23"
  },
  {
    "gameId": 2025020259,
    "teamAbbrev": "WSH",
    "homeRoadFlag": "R",
    "gameDate": "2025-11-11",
    "goals": 0,
    "assists": 0,
    "commonName": {
      "default": "Capitals"
    },
    "opponentCommonName": {
      "default": "Hurricanes"
    },
    "gamesStarted": 1,
    "decision": "W",
    "shotsAgainst": 31,
    "goalsAgainst": 1,
    "savePctg": 0.967742,
    "shutouts": 0,
    "opponentAbbrev": "CAR",
    "pim": 0,
    "toi": "60:00"
  },
  {
    "gameId": 2025020236,
    "teamAbbrev": "WSH",
    "homeRoadFlag": "R",
    "gameDate": "2025-11-08",
    "goals": 0,
    "assists": 0,
    "commonName": {
      "default": "Capitals"
    },
    "opponentCommonName": {
      "default": "Lightning"
    },
    "gamesStarted": 1,
    "decision": "L",
    "shotsAgainst": 20,
    "goalsAgainst": 3,
    "savePctg": 0.85,
    "shutouts": 0,
    "opponentAbbrev": "TBL",
    "pim": 0,
    "toi": "57:54"
  },
  {
    "gameId": 2025020214,
    "teamAbbrev": "WSH",
    "homeRoadFlag": "H",
    "gameDate": "2025-11-05",
    "goals": 0,
    "assists": 0,
    "commonName": {
      "default": "Capitals"
    },
    "opponentCommonName": {
      "default": "Blues"
    },
    "gamesStarted": 1,
    "decision": "W",
    "shotsAgainst": 24,
    "goalsAgainst": 1,
    "savePctg": 0.958333,
    "shutouts": 0,
    "opponentAbbrev": "STL",
    "pim": 0,
    "toi": "59:51"
  },
  {
    "gameId": 2025020179,
    "teamAbbrev": "WSH",
    "homeRoadFlag": "H",
    "gameDate": "2025-10-31",
    "goals": 0,
    "assists": 0,
    "commonName": {
      "default": "Capitals"
    },
    "opponentCommonName": {
      "default": "Islanders"
    },
    "gamesStarted": 1,
    "decision": "L",
    "shotsAgainst": 22,
    "goalsAgainst": 2,
    "savePctg": 0.909091,
    "shutouts": 0,
    "opponentAbbrev": "NYI",
    "pim": 0,
    "toi": "59:32"
  },
  {
    "gameId": 2025020159,
    "teamAbbrev": "WSH",
    "homeRoadFlag": "R",
    "gameDate": "2025-10-28",
    "goals": 0,
    "assists": 0,
    "commonName": {
      "default": "Capitals"
    },
    "opponentCommonName": {
      "default": "Stars"
    },
    "gamesStarted": 1,
    "decision": "L",
    "shotsAgainst": 19,
    "goalsAgainst": 1,
    "savePctg": 0.947368,
    "shutouts": 0,
    "opponentAbbrev": "DAL",
    "pim": 0,
    "toi": "58:14"
  },
  {
    "gameId": 2025020125,
    "teamAbbrev": "WSH",
    "homeRoadFlag": "R",
    "gameDate": "2025-10-24",
    "goals": 0,
    "assists": 1,
    "commonName": {
      "default": "Capitals"
    },
    "opponentCommonName": {
      "default": "Blue Jackets"
    },
    "gamesStarted": 1,
    "decision": "W",
    "shotsAgainst": 35,
    "goalsAgainst": 1,
    "savePctg": 0.971429,
    "shutouts": 0,
    "opponentAbbrev": "CBJ",
    "pim": 0,
    "toi": "60:00"
  },
  {
    "gameId": 2025020102,
    "teamAbbrev": "WSH",
    "homeRoadFlag": "H",
    "gameDate": "2025-10-21",
    "goals": 0,
    "assists": 0,
    "commonName": {
      "default": "Capitals"
    },
    "opponentCommonName": {
      "default": "Kraken"
    },
    "gamesStarted": 1,
    "decision": "W",
    "shotsAgainst": 19,
    "goalsAgainst": 1,
    "savePctg": 0.947368,
    "shutouts": 0,
    "opponentAbbrev": "SEA",
    "pim": 0,
    "toi": "60:00"
  },
  {
    "gameId": 2025020073,
    "teamAbbrev": "WSH",
    "homeRoadFlag": "H",
    "gameDate": "2025-10-17",
    "goals": 0,
    "assists": 0,
    "commonName": {
      "default": "Capitals"
    },
    "opponentCommonName": {
      "default": "Wild"
    },
    "gamesStarted": 1,
    "decision": "W",
    "shotsAgainst": 14,
    "goalsAgainst": 1,
    "savePctg": 0.928571,
    "shutouts": 0,
    "opponentAbbrev": "MIN",
    "pim": 0,
    "toi": "59:51"
  },
  {
    "gameId": 2025020052,
    "teamAbbrev": "WSH",
    "homeRoadFlag": "H",
    "gameDate": "2025-10-14",
    "goals": 0,
    "assists": 0,
    "commonName": {
      "default": "Capitals"
    },
    "opponentCommonName": {
      "default": "Lightning"
    },
    "gamesStarted": 1,
    "decision": "W",
    "shotsAgainst": 19,
    "goalsAgainst": 2,
    "savePctg": 0.894737,
    "shutouts": 0,
    "opponentAbbrev": "TBL",
    "pim": 0,
    "toi": "61:19"
  },
  {
    "gameId": 2025020028,
    "teamAbbrev": "WSH",
    "homeRoadFlag": "R",
    "gameDate": "2025-10-11",
    "goals": 0,
    "assists": 0,
    "commonName": {
      "default": "Capitals"
    },
    "opponentCommonName": {
      "default": "Islanders"
    },
    "gamesStarted": 1,
    "decision": "W",
    "shotsAgainst": 36,
    "goalsAgainst": 2,
    "savePctg": 0.944444,
    "shutouts": 0,
    "opponentAbbrev": "NYI",
    "pim": 0,
    "toi": "59:44"
  },
  {
    "gameId": 2025020005,
    "teamAbbrev": "WSH",
    "homeRoadFlag": "H",
    "gameDate": "2025-10-08",
    "goals": 0,
    "assists": 0,
    "commonName": {
      "default": "Capitals"
    },
    "opponentCommonName": {
      "default": "Bruins"
    },
    "gamesStarted": 1,
    "decision": "L",
    "shotsAgainst": 21,
    "goalsAgainst": 2,
    "savePctg": 0.904762,
    "shutouts": 0,
    "opponentAbbrev": "BOS",
    "pim": 0,
    "toi": "58:27"
  }
]